{"81":[12,"世田谷区","深沢"],"82":[12,"世田谷区","等々力"],"83":[12,"世田谷区","奥沢"],"84":[12,"世田谷区","東玉川"],"85":[12,"世田谷区","玉川田園調布"],"8501":[12,"世田谷区上用賀","1丁目18-1 国立医薬品食品衛生研究所"],"8502":[12,"世田谷区玉川","3丁目17-1 東神開発 株式会社"],"8503":[12,"世田谷区等々力","3-4-1 玉川総合支所"],"8505":[12,"世田谷区尾山台","3丁目7-2 ジャガージャパン 株式会社"],"8508":[12,"世田谷区深沢","7丁目1-1 日本体育大学"],"8509":[12,"世田谷区用賀","4丁目10-1 株式会社 東急コミュニティー"],"8510":[12,"世田谷区上野毛","3丁目9-25 (財) 五島美術館"],"8511":[12,"世田谷区玉川田園調布","1丁目20-9 学校法人 田園調布雙葉学園"],"8512":[12,"世田谷区東玉川","2丁目21-8 学校法人 調布学園"],"8513":[12,"世田谷区東玉川","2丁目6-7 昭栄電気工具 株式会社"],"8514":[12,"世田谷区用賀","4丁目5-16TEビル5F 石橋刷子製造 株式会社"],"8515":[12,"世田谷区玉川","2-21-1二子玉川ライズ・オフィス10F 日本年金機構 世田谷年金事務所"],"8518":[12,"世田谷区玉川","3丁目14-5 新日本気象海洋 株式会社"],"8520":[12,"世田谷区用賀","2丁目19-7 株式会社 ジャレコ"],"8522":[12,"世田谷区用賀","2丁目38-12 株式会社 アサヒ安全業務社"],"8523":[12,"世田谷区上用賀","2丁目12-17 日本中央競馬会 馬事公苑"],"8525":[12,"世田谷区用賀","2丁目32-4 明星電気 株式会社"],"8531":[12,"世田谷区上用賀","6丁目25-1 公立学校共済組合 関東中央病院"],"8533":[12,"世田谷区上野毛","1丁目7-11 シンコー 株式会社"],"8534":[12,"世田谷区用賀","4-10-1世田谷ビジネススクエアタワー 東急カード 株式会社"],"8539":[12,"世田谷区用賀","4-10-2世田谷ビジネススクエア・ヒルズ1(3階・4階) 東急ファシリティサービス 株式会社"],"8543":[12,"世田谷区等々力","6丁目16-9 岡谷電機産業 株式会社"],"8544":[12,"世田谷区中町","4丁目35-15 愛国産業 株式会社"],"8549":[12,"世田谷区用賀","2丁目31-7イイダアネックス12F 株式会社 サクラス"],"8550":[12,"世田谷区用賀","4丁目10-1 日本ジョンソン・アンド・ヒギンズ 株式会社"],"8551":[12,"世田谷区上野毛","4丁目35-10 株式会社 本間ゴルフ"],"8552":[12,"世田谷区深沢","5丁目13-10 長谷川病院"],"8557":[12,"世田谷区玉堤","1丁目28-1 東京都市大学"],"8558":[12,"世田谷区上野毛","3丁目15-34 学校法人 多摩美術大学"],"8561":[12,"世田谷区用賀","4丁目10番1号世田谷ビジネススクエア20階～21階 世田谷税務署"],"8566":[12,"世田谷区深沢","5丁目38-1 東京都立園芸高等学校"],"8567":[12,"世田谷区用賀","2丁目26-4 株式会社 レアーズ"],"8575":[12,"世田谷区玉川","2-21-1 株式会社 サンエー・インターナショナル"],"8577":[12,"世田谷区上用賀","1丁目17-12 学校法人 駒澤大学高等学校"],"8578":[12,"世田谷区用賀","2丁目28-9 株式会社 オリーブ情報システム"],"8580":[12,"世田谷区用賀","4丁目5-16TEビル7F 東京外かく環状道路調査事務所"],"8585":[12,"世田谷区中町","4丁目2-5 医療法人 社団和乃会小倉病院"],"8586":[12,"世田谷区等々力","8丁目9番18号 東京都市大学 等々力キャンパス"],"8588":[12,"世田谷区尾山台","3丁目7-5 ファーレン東京 株式会社"],"86":[12,"世田谷区","尾山台"],"8601":[12,"世田谷区玉川","2丁目1-7 玉川税務署"],"8602":[12,"世田谷区東玉川","2丁目37-11 株式会社 銀座マギー"],"8610":[12,"世田谷区玉川台","2丁目14-9 京セラミタ 株式会社 東京R&Dセンター"],"8615":[12,"世田谷区用賀","4丁目10番2号 タイコヘルスケアジャパン 株式会社"],"8622":[12,"世田谷区玉川","1-20-1 東京都世田谷都税事務所"],"8628":[12,"世田谷区用賀","4丁目32-25 株式会社 タカラ 東京本社"],"8630":[12,"世田谷区等々力","6丁目39-15 産業能率大学"],"8631":[12,"世田谷区等々力","6丁目39-15 産業能率大学"],"8632":[12,"世田谷区等々力","6丁目39-15 産業能率大学"],"8633":[12,"世田谷区用賀","4-10-1SBSタワー 日本オラクル 株式会社"],"8640":[12,"世田谷区上用賀","5丁目5-10 エディトリアルクリッパー"],"8666":[12,"世田谷区玉川台","2丁目18-1 株式会社 伸商"],"87":[12,"世田谷区","玉堤"],"8701":[12,"世田谷区玉川","3丁目17-1(玉川郵便局私書箱第29号) (株) 高島屋 玉川店"],"8771":[12,"世田谷区玉川","2-21-1二子玉川ライズ7階 株式会社 大正オーディット"],"91":[12,"世田谷区","中町"],"92":[12,"世田谷区","野毛"],"93":[12,"世田谷区","上野毛"],"94":[12,"世田谷区","玉川"],"95":[12,"世田谷区","瀬田"],"96":[12,"世田谷区","玉川台"],"97":[12,"世田谷区","用賀"],"98":[12,"世田谷区","上用賀"]}
