{"0":[12,"板橋区"],"41":[12,"板橋区","舟渡"],"42":[12,"板橋区","東坂下"],"43":[12,"板橋区","坂下"],"44":[12,"板橋区","相生町"],"45":[12,"板橋区","西台(1丁目)"],"46":[12,"板橋区","蓮根"],"51":[12,"板橋区","小豆沢"],"52":[12,"板橋区","蓮沼町"],"53":[12,"板橋区","清水町"],"54":[12,"板橋区","宮本町"],"55":[12,"板橋区","泉町"],"56":[12,"板橋区","志村"],"61":[12,"板橋区","大原町"],"62":[12,"板橋区","富士見町"],"63":[12,"板橋区","前野町"],"64":[12,"板橋区","中台"],"65":[12,"板橋区","若木"],"71":[12,"板橋区","常盤台"],"72":[12,"板橋区","南常盤台"],"73":[12,"板橋区","東山町"],"74":[12,"板橋区","東新町"],"75":[12,"板橋区","桜川"],"76":[12,"板橋区","上板橋"]}
