{"0":[7,"ひたちなか市"],"1":[7,"ひたちなか市","佐和"],"11":[7,"ひたちなか市","中根"],"12":[7,"ひたちなか市","馬渡"],"13":[7,"ひたちなか市","上野"],"14":[7,"ひたちなか市","後野"],"15":[7,"ひたちなか市","小砂町"],"16":[7,"ひたちなか市","松戸町"],"17":[7,"ひたちなか市","長堀町"],"18":[7,"ひたちなか市","笹野町"],"2":[7,"ひたちなか市","高野"],"21":[7,"ひたちなか市","三反田"],"22":[7,"ひたちなか市","金上"],"23":[7,"ひたちなか市","大平"],"24":[7,"ひたちなか市","勝倉"],"25":[7,"ひたちなか市","武田"],"26":[7,"ひたちなか市","勝田本町"],"27":[7,"ひたちなか市","勝田中原町"],"3":[7,"ひたちなか市","足崎"],"31":[7,"ひたちなか市","後台"],"32":[7,"ひたちなか市","津田"],"33":[7,"ひたちなか市","市毛"],"34":[7,"ひたちなか市","堀口"],"35":[7,"ひたちなか市","枝川"],"36":[7,"ひたちなか市","津田東"],"4":[7,"ひたちなか市","長砂"],"41":[7,"ひたちなか市","西大島"],"42":[7,"ひたちなか市","東大島"],"43":[7,"ひたちなか市","共栄町"],"44":[7,"ひたちなか市","元町"],"45":[7,"ひたちなか市","勝田中央"],"46":[7,"ひたちなか市","勝田泉町"],"47":[7,"ひたちなか市","表町"],"48":[7,"ひたちなか市","春日町"],"5":[7,"ひたちなか市","新光町"],"51":[7,"ひたちなか市","堂端"],"52":[7,"ひたちなか市","東石川"],"53":[7,"ひたちなか市","外野"],"54":[7,"ひたちなか市","はしかべ"],"55":[7,"ひたちなか市","大成町"],"56":[7,"ひたちなか市","青葉町"],"57":[7,"ひたちなか市","石川町"],"58":[7,"ひたちなか市","西光地"],"6":[7,"ひたちなか市","前浜"],"61":[7,"ひたちなか市","稲田"],"62":[7,"ひたちなか市","高場"],"63":[7,"ひたちなか市","田彦"],"7":[7,"ひたちなか市","小貫山"]}
