{"1":[10,"川口市","桜町"],"11":[10,"川口市","三ツ和"],"12":[10,"川口市","八幡木"],"13":[10,"川口市","南鳩ヶ谷"],"14":[10,"川口市","前田"],"15":[10,"川口市","鳩ヶ谷緑町"],"2":[10,"川口市","鳩ヶ谷本町"],"3":[10,"川口市","坂下町"],"4":[10,"川口市","辻"],"5":[10,"川口市","里"],"51":[10,"川口市","安行藤八"],"52":[10,"川口市","安行出羽"],"53":[10,"川口市","安行吉蔵"],"54":[10,"川口市","安行北谷"],"55":[10,"川口市","安行小山"],"56":[10,"川口市","峯"],"57":[10,"川口市","安行原"],"58":[10,"川口市","安行領家"],"59":[10,"川口市","安行"],"61":[10,"川口市","新堀"],"62":[10,"川口市","榛松"],"63":[10,"川口市","東本郷"],"64":[10,"川口市","蓮沼"],"65":[10,"川口市","前野宿"],"66":[10,"川口市","東貝塚"],"67":[10,"川口市","大竹"],"68":[10,"川口市","新堀町"],"71":[10,"川口市","安行慈林"],"72":[10,"川口市","安行吉岡"],"73":[10,"川口市","赤井"],"74":[10,"川口市","江戸"],"75":[10,"川口市","江戸袋"],"76":[10,"川口市","本蓮"],"8501":[10,"川口市南鳩ヶ谷","3丁目21-4 協和ゴム工業 株式会社"]}
