{"0":[22,"犬山市"],"1":[22,"犬山市","垣ノ内"],"11":[22,"犬山市","北高根"],"12":[22,"犬山市","南高根"],"13":[22,"犬山市","寺洞"],"14":[22,"犬山市","郷中"],"15":[22,"犬山市","御殿屋敷"],"16":[22,"犬山市","藪ケ洞"],"17":[22,"犬山市","篠平"],"18":[22,"犬山市","佐ケ瀬"],"19":[22,"犬山市","四季の丘"],"2":[22,"犬山市","栗栖"],"20":[22,"犬山市","もえぎケ丘"],"21":[22,"犬山市","杁下"],"22":[22,"犬山市","白山洞"],"23":[22,"犬山市","堤下"],"24":[22,"犬山市","喜六屋敷"],"25":[22,"犬山市","野中"],"26":[22,"犬山市","内屋敷"],"27":[22,"犬山市","倉曽洞"],"28":[22,"犬山市","向田"],"29":[22,"犬山市","西洞"],"3":[22,"犬山市","善師野"],"31":[22,"犬山市","東桑原"],"32":[22,"犬山市","池野安楽寺"],"33":[22,"犬山市","井ノ元"],"34":[22,"犬山市","大洞"],"35":[22,"犬山市","裏山"],"36":[22,"犬山市","西桑原"],"37":[22,"犬山市","西片草"],"38":[22,"犬山市","東片草"],"4":[22,"犬山市","善師野台"],"41":[22,"犬山市","長者町"],"42":[22,"犬山市","二本木"],"43":[22,"犬山市","上ノ田"],"44":[22,"犬山市","下屋敷"],"45":[22,"犬山市","仲畑"],"46":[22,"犬山市","屋敷裏"],"47":[22,"犬山市","内久保"],"48":[22,"犬山市","楽田内久保"],"49":[22,"犬山市","前田面"],"5":[22,"犬山市","今井"],"51":[22,"犬山市","宮裏"],"52":[22,"犬山市","早稲田"],"53":[22,"犬山市","石畑"],"54":[22,"犬山市","仲屋敷"],"55":[22,"犬山市","牛岩"],"56":[22,"犬山市","稲干場"],"57":[22,"犬山市","富士山"],"58":[22,"犬山市","大門"],"59":[22,"犬山市","上坂町"],"6":[22,"犬山市","八曽"],"61":[22,"犬山市","前原"],"62":[22,"犬山市","前原味鹿"],"63":[22,"犬山市","前原南"],"64":[22,"犬山市","前原西"],"65":[22,"犬山市","五郎丸東"],"66":[22,"犬山市","五郎丸"],"7":[22,"犬山市","十三塚"],"71":[22,"犬山市","内田東町"],"72":[22,"犬山市","丸山天白町"],"73":[22,"犬山市","天神町"],"74":[22,"犬山市","梅坪"],"75":[22,"犬山市","橋爪東"],"76":[22,"犬山市","橋爪"],"77":[22,"犬山市","上野"],"78":[22,"犬山市","上野新町"],"79":[22,"犬山市","木津"],"8":[22,"犬山市","岩穴"],"801":[22,"犬山市","羽黒安戸南"],"802":[22,"犬山市","羽黒安戸西"],"803":[22,"犬山市","羽黒新赤坂"],"804":[22,"犬山市","羽黒桜海道"],"805":[22,"犬山市","羽黒新外山"],"806":[22,"犬山市","羽黒朝日"],"807":[22,"犬山市","羽黒鉾添"],"81":[22,"犬山市","犬山"],"811":[22,"犬山市","楽田長塚東"],"812":[22,"犬山市","山ノ田"],"813":[22,"犬山市","山ノ田腰"],"814":[22,"犬山市","高根"],"815":[22,"犬山市","郷東"],"816":[22,"犬山市","楽田原東"],"817":[22,"犬山市","郷西"],"818":[22,"犬山市","北浦"],"819":[22,"犬山市","楽田長塚西"],"82":[22,"犬山市","北古券"],"821":[22,"犬山市","山崎西"],"822":[22,"犬山市","中切"],"823":[22,"犬山市","北大門"],"824":[22,"犬山市","北洞"],"825":[22,"犬山市","常福寺洞"],"826":[22,"犬山市","山ノ鼻"],"827":[22,"犬山市","薬師前"],"828":[22,"犬山市","薬師浦"],"83":[22,"犬山市","東古券"],"831":[22,"犬山市","堂屋敷"],"832":[22,"犬山市","向山"],"833":[22,"犬山市","宮西"],"834":[22,"犬山市","宮山"],"835":[22,"犬山市","蓮池"],"836":[22,"犬山市","笛田"],"837":[22,"犬山市","荒井"],"838":[22,"犬山市","小路"],"839":[22,"犬山市","桃山台"],"84":[22,"犬山市","南古券"],"841":[22,"犬山市","楽田小針"],"842":[22,"犬山市","下小針"],"843":[22,"犬山市","楽田打越"],"844":[22,"犬山市","鷺山"],"845":[22,"犬山市","高坪"],"846":[22,"犬山市","楽田山ノ田"],"85":[22,"犬山市","西古券"],"8501":[22,"犬山市大字犬山","字東畑36 犬山市役所"],"8502":[22,"犬山市大字橋爪","字中島2 村田機械 株式会社 犬山工場"],"8503":[22,"犬山市字内久保","61-1 名古屋経済大学 短期大学部"],"8504":[22,"犬山市字内久保","61-1 名古屋経済大学"],"8505":[22,"犬山市字上小針","1 エナジーサポート 株式会社"],"8506":[22,"犬山市大字犬山","字官林41 京都大学霊長類研究所"],"8507":[22,"犬山市字柿畑","1 (株) 今仙電機製作所"],"8508":[22,"犬山市大字木津","字前畑344 東洋紡 株式会社 犬山工場"],"851":[22,"犬山市","烏杜"],"8510":[22,"犬山市天神町","1丁目8 犬山商工会議所"],"8511":[22,"犬山市大字五郎丸","字二タ子塚6 医療法人社団 志聖会 犬山中央病院"],"8512":[22,"犬山市大字犬山","字北白山平5番地 成田山 大聖寺"],"852":[22,"犬山市","中小針"],"853":[22,"犬山市","横町"],"854":[22,"犬山市","裏之門"],"855":[22,"犬山市","小洞"],"856":[22,"犬山市","楽田天神"],"857":[22,"犬山市","外屋敷"],"858":[22,"犬山市","城山"],"86":[22,"犬山市","松本町"],"8609":[22,"犬山市松本町","2丁目10番地 犬山公共職業安定所"],"861":[22,"犬山市","若宮"],"862":[22,"犬山市","石塚"],"863":[22,"犬山市","野田"],"864":[22,"犬山市","番前"],"865":[22,"犬山市","藪畔"],"866":[22,"犬山市","寺西"],"867":[22,"犬山市","九左エ門廻り"],"868":[22,"犬山市","東北野"],"869":[22,"犬山市","惣作"],"87":[22,"犬山市","中山町"],"871":[22,"犬山市","前並"],"872":[22,"犬山市","岩田"],"873":[22,"犬山市","天王前"],"874":[22,"犬山市","楽田今村"],"875":[22,"犬山市","林吾塚"],"876":[22,"犬山市","山神"],"877":[22,"犬山市","楽田東追分"],"878":[22,"犬山市","栗林"],"879":[22,"犬山市","楽田三ツ塚"],"881":[22,"犬山市","羽黒成海西"],"882":[22,"犬山市","羽黒菊川"],"883":[22,"犬山市","羽黒成海南"],"884":[22,"犬山市","羽黒起"],"885":[22,"犬山市","楽田原西"],"886":[22,"犬山市","宮浦"],"887":[22,"犬山市","池田"],"888":[22,"犬山市","羽黒新田"],"889":[22,"犬山市","羽黒高橋"],"891":[22,"犬山市","羽黒恩田島"],"892":[22,"犬山市","羽黒惣境"],"893":[22,"犬山市","羽黒栄"],"894":[22,"犬山市","羽黒"],"895":[22,"犬山市","羽黒摺墨"],"896":[22,"犬山市","羽黒余町"],"897":[22,"犬山市","羽黒堂前"],"898":[22,"犬山市","羽黒稲葉西"],"899":[22,"犬山市","羽黒稲葉東"],"9":[22,"犬山市","田口"],"901":[22,"犬山市","柿畑"],"902":[22,"犬山市","追分"],"903":[22,"犬山市","追分東"],"904":[22,"犬山市","楽田勝部前"],"905":[22,"犬山市","西北野"],"906":[22,"犬山市","焼野"],"907":[22,"犬山市","楽田地蔵池"],"908":[22,"犬山市","大上戸"],"91":[22,"犬山市","継鹿尾"],"911":[22,"犬山市","北之門"],"912":[22,"犬山市","舟田"],"913":[22,"犬山市","鳥屋越"],"914":[22,"犬山市","観音浦"],"915":[22,"犬山市","楽田上沼"],"916":[22,"犬山市","楽田西浦"],"917":[22,"犬山市","土取"],"918":[22,"犬山市","ニタ田"],"919":[22,"犬山市","中道"],"92":[22,"犬山市","富岡"],"921":[22,"犬山市","味加田"],"922":[22,"犬山市","北大橋"],"923":[22,"犬山市","下沼"],"924":[22,"犬山市","楽田大橋"],"925":[22,"犬山市","楽田西野"],"926":[22,"犬山市","楽田一色浦"],"927":[22,"犬山市","的場"],"928":[22,"犬山市","七ツ屋"],"93":[22,"犬山市","富岡東"],"931":[22,"犬山市","南大橋"],"932":[22,"犬山市","西野"],"933":[22,"犬山市","東唐曽"],"934":[22,"犬山市","中唐曽"],"935":[22,"犬山市","西唐曽"],"936":[22,"犬山市","楽田青塚"],"937":[22,"犬山市","宮東"],"94":[22,"犬山市","塔野地"],"941":[22,"犬山市","巾廻り"],"942":[22,"犬山市","楽田巾"],"943":[22,"犬山市","巾前"],"944":[22,"犬山市","楽田安師"],"945":[22,"犬山市","青塚"],"946":[22,"犬山市","東大円"],"947":[22,"犬山市","楽田大円"],"948":[22,"犬山市","西大円"],"95":[22,"犬山市","塔野地杉"],"951":[22,"犬山市","八反田"],"952":[22,"犬山市","上舞台"],"953":[22,"犬山市","下舞台"],"954":[22,"犬山市","元散前"],"955":[22,"犬山市","角池"],"956":[22,"犬山市","新川"],"957":[22,"犬山市","五反田"],"958":[22,"犬山市","平塚"],"959":[22,"犬山市","北平塚"],"96":[22,"犬山市","塔野地西"],"961":[22,"犬山市","太吉屋敷"],"962":[22,"犬山市","落添"],"963":[22,"犬山市","楽田鶴池"],"964":[22,"犬山市","上榎島"],"965":[22,"犬山市","下榎島"],"966":[22,"犬山市","五郎丸二タ俣"],"97":[22,"犬山市","塔野地北"],"98":[22,"犬山市","富岡南"],"99":[22,"犬山市","富岡新町"]}
