{"1":[22,"稲沢市","祖父江町祖父江"],"11":[22,"稲沢市","祖父江町森上"],"12":[22,"稲沢市","祖父江町本甲"],"13":[22,"稲沢市","祖父江町二俣"],"14":[22,"稲沢市","祖父江町大牧"],"15":[22,"稲沢市","祖父江町桜方"],"2":[22,"稲沢市","祖父江町山崎"],"21":[22,"稲沢市","祖父江町三丸渕"],"22":[22,"稲沢市","祖父江町甲新田"],"23":[22,"稲沢市","祖父江町島本"],"24":[22,"稲沢市","祖父江町野田"],"25":[22,"稲沢市","祖父江町両寺内"],"3":[22,"稲沢市","祖父江町高熊西"],"31":[22,"稲沢市","祖父江町上牧"],"32":[22,"稲沢市","祖父江町中牧"],"33":[22,"稲沢市","祖父江町四貫"],"34":[22,"稲沢市","祖父江町西鵜之本"],"35":[22,"稲沢市","祖父江町神明津"],"36":[22,"稲沢市","祖父江町馬飼"],"37":[22,"稲沢市","祖父江町拾町野"],"8501":[22,"稲沢市祖父江町森上","本郷十一4番地1 アイコクアルファ 株式会社"],"8505":[22,"稲沢市祖父江町二俣","宮西1番地1 愛知県立 杏和高等学校"],"8510":[22,"稲沢市祖父江町四貫","堤外22番地 帝人テクロス 株式会社"],"8511":[22,"稲沢市祖父江町山崎","鶴塚275番地1 稲沢市 祖父江支所"],"8517":[22,"稲沢市祖父江町甲新田","イ九-65 株式会社 コメットカトウ"],"8531":[22,"稲沢市祖父江町本甲","拾町野7番地 愛知県 厚生連 尾西病院"],"8601":[22,"稲沢市祖父江町祖父江","外平150番地 王子マテリア 株式会社 祖父江工場"]}
