{"0":[23,"鈴鹿市"],"1":[23,"鈴鹿市","広瀬町"],"10":[23,"鈴鹿市","釆女が丘町"],"11":[23,"鈴鹿市","高塚町"],"1121":[23,"鈴鹿市","岸田町"],"1122":[23,"鈴鹿市","花川町"],"1123":[23,"鈴鹿市","下大久保町"],"1124":[23,"鈴鹿市","自由ヶ丘"],"12":[23,"鈴鹿市","石薬師町"],"13":[23,"鈴鹿市","国分町"],"14":[23,"鈴鹿市","高岡町"],"15":[23,"鈴鹿市","木田町"],"16":[23,"鈴鹿市","山辺町"],"17":[23,"鈴鹿市","上野町"],"18":[23,"鈴鹿市","上田町"],"19":[23,"鈴鹿市","高岡台"],"2":[23,"鈴鹿市","津賀町"],"21":[23,"鈴鹿市","甲斐町"],"22":[23,"鈴鹿市","野辺町"],"23":[23,"鈴鹿市","河田町"],"24":[23,"鈴鹿市","野辺"],"25":[23,"鈴鹿市","竹野"],"26":[23,"鈴鹿市","竹野町"],"27":[23,"鈴鹿市","岡田"],"28":[23,"鈴鹿市","岡田町"],"3":[23,"鈴鹿市","加佐登町"],"31":[23,"鈴鹿市","一ノ宮町"],"32":[23,"鈴鹿市","池田町"],"33":[23,"鈴鹿市","須賀町"],"34":[23,"鈴鹿市","須賀"],"35":[23,"鈴鹿市","矢橋町"],"36":[23,"鈴鹿市","矢橋"],"37":[23,"鈴鹿市","十宮"],"38":[23,"鈴鹿市","十宮町"],"4":[23,"鈴鹿市","加佐登"],"41":[23,"鈴鹿市","長太新町"],"42":[23,"鈴鹿市","長太旭町"],"43":[23,"鈴鹿市","長太栄町"],"44":[23,"鈴鹿市","北堀江町"],"45":[23,"鈴鹿市","北堀江"],"46":[23,"鈴鹿市","南堀江"],"47":[23,"鈴鹿市","南堀江町"],"48":[23,"鈴鹿市","南長太町"],"49":[23,"鈴鹿市","北長太町"],"5":[23,"鈴鹿市","汲川原町"],"51":[23,"鈴鹿市","下箕田町"],"52":[23,"鈴鹿市","下箕田"],"53":[23,"鈴鹿市","中箕田町"],"54":[23,"鈴鹿市","中箕田"],"55":[23,"鈴鹿市","上箕田町"],"56":[23,"鈴鹿市","上箕田"],"57":[23,"鈴鹿市","南林崎町"],"58":[23,"鈴鹿市","林崎"],"59":[23,"鈴鹿市","林崎町"],"6":[23,"鈴鹿市","和泉町"],"7":[23,"鈴鹿市","小田町"],"8":[23,"鈴鹿市","西冨田町"],"801":[[23,"鈴鹿市","神戸"],[23,"鈴鹿市","神戸本多町"]],"802":[23,"鈴鹿市","飯野寺家町"],"803":[23,"鈴鹿市","三日市町"],"804":[23,"鈴鹿市","三日市南"],"805":[23,"鈴鹿市","算所町"],"806":[23,"鈴鹿市","算所"],"807":[23,"鈴鹿市","三日市"],"808":[23,"鈴鹿市","西條町"],"809":[23,"鈴鹿市","西条"],"811":[23,"鈴鹿市","柳町"],"812":[23,"鈴鹿市","土師町"],"813":[23,"鈴鹿市","北玉垣町"],"814":[23,"鈴鹿市","東玉垣町"],"815":[23,"鈴鹿市","西玉垣町"],"816":[23,"鈴鹿市","南玉垣町"],"817":[23,"鈴鹿市","桜島町"],"818":[23,"鈴鹿市","安塚町"],"819":[23,"鈴鹿市","肥田町"],"821":[23,"鈴鹿市","地子町"],"822":[23,"鈴鹿市","末広町"],"823":[23,"鈴鹿市","道伯"],"824":[23,"鈴鹿市","道伯町"],"825":[23,"鈴鹿市","住吉町"],"826":[23,"鈴鹿市","住吉"],"827":[23,"鈴鹿市","大池"],"828":[23,"鈴鹿市","阿古曽町"],"831":[23,"鈴鹿市","庄野町"],"832":[23,"鈴鹿市","庄野東"],"833":[23,"鈴鹿市","庄野共進"],"834":[23,"鈴鹿市","庄野羽山"],"835":[23,"鈴鹿市","平野町"],"836":[23,"鈴鹿市","国府町"],"837":[23,"鈴鹿市","八野町"],"841":[23,"鈴鹿市","弓削町"],"842":[23,"鈴鹿市","弓削"],"843":[23,"鈴鹿市","平田東町"],"844":[23,"鈴鹿市","平田"],"845":[23,"鈴鹿市","平田新町"],"846":[23,"鈴鹿市","平田中町"],"847":[23,"鈴鹿市","平田町"],"848":[23,"鈴鹿市","平田本町"],"851":[23,"鈴鹿市","末広東"],"852":[23,"鈴鹿市","末広西"],"853":[23,"鈴鹿市","末広南"],"854":[23,"鈴鹿市","末広北"],"855":[23,"鈴鹿市","石垣"],"9":[23,"鈴鹿市","中冨田町"]}
