{"41":[26,"大阪市北区","天神橋(7、8丁目)"],"6001":[26,"大阪市北区","大淀中梅田スカイビルタワーイースト(1階)"],"6002":[26,"大阪市北区","大淀中梅田スカイビルタワーイースト(2階)"],"6003":[26,"大阪市北区","大淀中梅田スカイビルタワーイースト(3階)"],"6004":[26,"大阪市北区","大淀中梅田スカイビルタワーイースト(4階)"],"6005":[26,"大阪市北区","大淀中梅田スカイビルタワーイースト(5階)"],"6006":[26,"大阪市北区","大淀中梅田スカイビルタワーイースト(6階)"],"6007":[26,"大阪市北区","大淀中梅田スカイビルタワーイースト(7階)"],"6008":[26,"大阪市北区","大淀中梅田スカイビルタワーイースト(8階)"],"6009":[26,"大阪市北区","大淀中梅田スカイビルタワーイースト(9階)"],"6010":[26,"大阪市北区","大淀中梅田スカイビルタワーイースト(10階)"],"6011":[26,"大阪市北区","大淀中梅田スカイビルタワーイースト(11階)"],"6012":[26,"大阪市北区","大淀中梅田スカイビルタワーイースト(12階)"],"6013":[26,"大阪市北区","大淀中梅田スカイビルタワーイースト(13階)"],"6014":[26,"大阪市北区","大淀中梅田スカイビルタワーイースト(14階)"],"6015":[26,"大阪市北区","大淀中梅田スカイビルタワーイースト(15階)"],"6016":[26,"大阪市北区","大淀中梅田スカイビルタワーイースト(16階)"],"6017":[26,"大阪市北区","大淀中梅田スカイビルタワーイースト(17階)"],"6018":[26,"大阪市北区","大淀中梅田スカイビルタワーイースト(18階)"],"6019":[26,"大阪市北区","大淀中梅田スカイビルタワーイースト(19階)"],"6020":[26,"大阪市北区","大淀中梅田スカイビルタワーイースト(20階)"],"6021":[26,"大阪市北区","大淀中梅田スカイビルタワーイースト(21階)"],"6022":[26,"大阪市北区","大淀中梅田スカイビルタワーイースト(22階)"],"6023":[26,"大阪市北区","大淀中梅田スカイビルタワーイースト(23階)"],"6024":[26,"大阪市北区","大淀中梅田スカイビルタワーイースト(24階)"],"6025":[26,"大阪市北区","大淀中梅田スカイビルタワーイースト(25階)"],"6026":[26,"大阪市北区","大淀中梅田スカイビルタワーイースト(26階)"],"6027":[26,"大阪市北区","大淀中梅田スカイビルタワーイースト(27階)"],"6028":[26,"大阪市北区","大淀中梅田スカイビルタワーイースト(28階)"],"6029":[26,"大阪市北区","大淀中梅田スカイビルタワーイースト(29階)"],"6030":[26,"大阪市北区","大淀中梅田スカイビルタワーイースト(30階)"],"6031":[26,"大阪市北区","大淀中梅田スカイビルタワーイースト(31階)"],"6032":[26,"大阪市北区","大淀中梅田スカイビルタワーイースト(32階)"],"6033":[26,"大阪市北区","大淀中梅田スカイビルタワーイースト(33階)"],"6034":[26,"大阪市北区","大淀中梅田スカイビルタワーイースト(34階)"],"6035":[26,"大阪市北区","大淀中梅田スカイビルタワーイースト(35階)"],"6036":[26,"大阪市北区","大淀中梅田スカイビルタワーイースト(36階)"],"6037":[26,"大阪市北区","大淀中梅田スカイビルタワーイースト(37階)"],"6038":[26,"大阪市北区","大淀中梅田スカイビルタワーイースト(38階)"],"6039":[26,"大阪市北区","大淀中梅田スカイビルタワーイースト(39階)"],"6053":[26,"大阪市北区大淀中","1丁目1番90号梅田スカイビルガーデンファイブ3階 積水ハウスリフォーム 株式会社"],"6090":[26,"大阪市北区","大淀中梅田スカイビルタワーイースト(地階・階層不明)"],"61":[26,"大阪市北区","長柄西"],"6101":[26,"大阪市北区","大淀中梅田スカイビルタワーウエスト(1階)"],"6102":[26,"大阪市北区","大淀中梅田スカイビルタワーウエスト(2階)"],"6103":[26,"大阪市北区","大淀中梅田スカイビルタワーウエスト(3階)"],"6104":[26,"大阪市北区","大淀中梅田スカイビルタワーウエスト(4階)"],"6105":[26,"大阪市北区","大淀中梅田スカイビルタワーウエスト(5階)"],"6106":[26,"大阪市北区","大淀中梅田スカイビルタワーウエスト(6階)"],"6107":[26,"大阪市北区","大淀中梅田スカイビルタワーウエスト(7階)"],"6108":[26,"大阪市北区","大淀中梅田スカイビルタワーウエスト(8階)"],"6109":[26,"大阪市北区","大淀中梅田スカイビルタワーウエスト(9階)"],"6110":[26,"大阪市北区","大淀中梅田スカイビルタワーウエスト(10階)"],"6111":[26,"大阪市北区","大淀中梅田スカイビルタワーウエスト(11階)"],"6112":[26,"大阪市北区","大淀中梅田スカイビルタワーウエスト(12階)"],"6113":[26,"大阪市北区","大淀中梅田スカイビルタワーウエスト(13階)"],"6114":[26,"大阪市北区","大淀中梅田スカイビルタワーウエスト(14階)"],"6115":[26,"大阪市北区","大淀中梅田スカイビルタワーウエスト(15階)"],"6116":[26,"大阪市北区","大淀中梅田スカイビルタワーウエスト(16階)"],"6117":[26,"大阪市北区","大淀中梅田スカイビルタワーウエスト(17階)"],"6118":[26,"大阪市北区","大淀中梅田スカイビルタワーウエスト(18階)"],"6119":[26,"大阪市北区","大淀中梅田スカイビルタワーウエスト(19階)"],"6120":[26,"大阪市北区","大淀中梅田スカイビルタワーウエスト(20階)"],"6121":[26,"大阪市北区","大淀中梅田スカイビルタワーウエスト(21階)"],"6122":[26,"大阪市北区","大淀中梅田スカイビルタワーウエスト(22階)"],"6123":[26,"大阪市北区","大淀中梅田スカイビルタワーウエスト(23階)"],"6124":[26,"大阪市北区","大淀中梅田スカイビルタワーウエスト(24階)"],"6125":[26,"大阪市北区","大淀中梅田スカイビルタワーウエスト(25階)"],"6126":[26,"大阪市北区","大淀中梅田スカイビルタワーウエスト(26階)"],"6127":[26,"大阪市北区","大淀中梅田スカイビルタワーウエスト(27階)"],"6128":[26,"大阪市北区","大淀中梅田スカイビルタワーウエスト(28階)"],"6129":[26,"大阪市北区","大淀中梅田スカイビルタワーウエスト(29階)"],"6130":[26,"大阪市北区","大淀中梅田スカイビルタワーウエスト(30階)"],"6131":[26,"大阪市北区","大淀中梅田スカイビルタワーウエスト(31階)"],"6132":[26,"大阪市北区","大淀中梅田スカイビルタワーウエスト(32階)"],"6133":[26,"大阪市北区","大淀中梅田スカイビルタワーウエスト(33階)"],"6134":[26,"大阪市北区","大淀中梅田スカイビルタワーウエスト(34階)"],"6135":[26,"大阪市北区","大淀中梅田スカイビルタワーウエスト(35階)"],"6136":[26,"大阪市北区","大淀中梅田スカイビルタワーウエスト(36階)"],"6137":[26,"大阪市北区","大淀中梅田スカイビルタワーウエスト(37階)"],"6138":[26,"大阪市北区","大淀中梅田スカイビルタワーウエスト(38階)"],"6139":[26,"大阪市北区","大淀中梅田スカイビルタワーウエスト(39階)"],"6190":[26,"大阪市北区","大淀中梅田スカイビルタワーウエスト(地階・階層不明)"],"62":[26,"大阪市北区","長柄中"],"63":[26,"大阪市北区","長柄東"],"64":[26,"大阪市北区","国分寺"],"71":[26,"大阪市北区","中津"],"72":[26,"大阪市北区","豊崎"],"73":[26,"大阪市北区","本庄西"],"74":[26,"大阪市北区","本庄東"],"75":[26,"大阪市北区","大淀南"],"76":[26,"大阪市北区","大淀中(次のビルを除く)"],"77":[26,"大阪市北区","大淀北"],"8501":[26,"大阪市北区大淀南","2丁目3-3 株式会社 ザ・シンフォニーホール"],"8502":[26,"大阪市北区本庄東","2丁目9番18号 関電プラント 株式会社"],"8503":[26,"大阪市北区豊崎","3丁目19番3号 カバーマーク 株式会社"],"8510":[26,"大阪市北区本庄西","3丁目9番3号 ニプロ 株式会社"],"8511":[26,"大阪市北区大淀北","2丁目1-2 ニッポンペイント 株式会社"],"8519":[26,"大阪市北区豊崎","3丁目19番3号 東急建設 株式会社 大阪支店"],"8526":[26,"大阪市北区大淀北","2丁目1番27号 東罐マテリアル・テクノロジー (株)"],"8555":[26,"大阪市北区大淀中","1丁目4-13 三菱電機クレジット 株式会社"],"8558":[26,"大阪市北区野崎町","5-9読売大阪ビル 報知新聞 大阪本社"],"8567":[26,"大阪市北区大淀中","1丁目7-4 株式会社 日本電商"],"8577":[26,"大阪市北区豊崎","5-4-19 株式会社 インテック"],"8588":[26,"大阪市北区本庄東","3丁目9-3 関西電力 株式会社 大阪北支店"],"8787":[26,"大阪市北区大淀中","1丁目3-6 大阪地域センター"]}
