{"801":[26,"豊中市","曽根西町"],"802":[26,"豊中市","曽根東町"],"803":[26,"豊中市","城山町"],"804":[26,"豊中市","曽根南町"],"805":[26,"豊中市","原田南"],"806":[26,"豊中市","原田西町"],"807":[26,"豊中市","原田中"],"808":[26,"豊中市","原田元町"],"811":[26,"豊中市","若竹町"],"812":[26,"豊中市","北条町"],"813":[26,"豊中市","小曽根"],"814":[26,"豊中市","豊南町東"],"815":[26,"豊中市","豊南町南"],"816":[26,"豊中市","豊南町西"],"817":[26,"豊中市","浜"],"821":[26,"豊中市","日出町"],"822":[26,"豊中市","三国"],"823":[26,"豊中市","神州町"],"824":[26,"豊中市","大島町"],"825":[26,"豊中市","二葉町"],"826":[26,"豊中市","島江町"],"827":[26,"豊中市","大黒町"],"828":[26,"豊中市","三和町"],"829":[26,"豊中市","千成町"],"831":[26,"豊中市","庄内東町"],"832":[26,"豊中市","庄内西町"],"833":[26,"豊中市","庄内幸町"],"834":[26,"豊中市","庄内栄町"],"835":[26,"豊中市","庄本町"],"836":[26,"豊中市","庄内宝町"],"841":[26,"豊中市","名神口"],"842":[26,"豊中市","今在家町"],"843":[26,"豊中市","上津島"],"844":[26,"豊中市","利倉西"],"845":[26,"豊中市","利倉"],"846":[26,"豊中市","利倉東"],"8501":[26,"豊中市中桜塚","3丁目1-1 豊中市役所"],"851":[26,"豊中市","服部元町"],"8510":[26,"豊中市寺内","2丁目13-3 株式会社 日本経営"],"8511":[26,"豊中市岡町北","1丁目2-17太陽生命豊中ビル2F 大阪北生活協同組合"],"852":[26,"豊中市","服部本町"],"8520":[26,"豊中市岡町","1番1号 摂津水都信用金庫"],"853":[26,"豊中市","服部南町"],"854":[26,"豊中市","稲津町"],"855":[26,"豊中市","野田町"],"8550":[26,"豊中市日出町","1丁目6-22 株式会社 イーパック"],"8555":[26,"豊中市庄内幸町","1丁目1-8 学校法人 大阪音楽大学"],"8558":[26,"豊中市千成町","3丁目5-3 松尾電機 株式会社"],"856":[26,"豊中市","穂積"],"8561":[26,"豊中市庄内西町","5丁目1-24 阪急バス 株式会社"],"857":[26,"豊中市","服部寿町"],"8577":[26,"豊中市利倉東","1丁目2番1号 学校法人 大商学園 大商学園高等学校"],"858":[26,"豊中市","服部西町"],"859":[26,"豊中市","服部豊町"],"861":[26,"豊中市","東泉丘"],"862":[26,"豊中市","西泉丘"],"863":[26,"豊中市","広田町"],"864":[26,"豊中市","夕日丘"],"865":[26,"豊中市","旭丘"],"871":[26,"豊中市","東寺内町"],"872":[26,"豊中市","寺内"],"873":[26,"豊中市","服部緑地"],"874":[26,"豊中市","長興寺南"],"875":[26,"豊中市","長興寺北"],"881":[26,"豊中市","中桜塚"],"882":[26,"豊中市","南桜塚"],"883":[26,"豊中市","岡町南"],"884":[26,"豊中市","岡町北"],"885":[26,"豊中市","岡町"],"891":[26,"豊中市","走井"],"892":[26,"豊中市","山ノ上町"],"893":[26,"豊中市","宝山町"],"894":[26,"豊中市","勝部"]}
