{"0":[39,"北九州市八幡東区"],"1":[39,"北九州市八幡東区","荒手"],"11":[39,"北九州市八幡東区","八王寺町"],"12":[39,"北九州市八幡東区","川淵町"],"13":[39,"北九州市八幡東区","昭和"],"14":[39,"北九州市八幡東区","茶屋町"],"15":[39,"北九州市八幡東区","荒生田"],"16":[39,"北九州市八幡東区","高見"],"17":[39,"北九州市八幡東区","山王"],"18":[39,"北九州市八幡東区","上本町"],"19":[39,"北九州市八幡東区","中央"],"2":[39,"北九州市八幡東区","枝光"],"21":[39,"北九州市八幡東区","石坪町"],"22":[39,"北九州市八幡東区","竹下町"],"23":[39,"北九州市八幡東区","宮の町"],"24":[39,"北九州市八幡東区","中畑"],"25":[39,"北九州市八幡東区","中尾"],"26":[39,"北九州市八幡東区","東山"],"27":[39,"北九州市八幡東区","東鉄町"],"3":[39,"北九州市八幡東区","大宮町"],"31":[39,"北九州市八幡東区","槻田"],"32":[39,"北九州市八幡東区","松尾町"],"33":[39,"北九州市八幡東区","山路松尾町"],"34":[39,"北九州市八幡東区","清田"],"35":[39,"北九州市八幡東区","山路"],"36":[39,"北九州市八幡東区","小熊野"],"37":[39,"北九州市八幡東区","猪倉町"],"38":[39,"北九州市八幡東区","大平町"],"4":[39,"北九州市八幡東区","日の出"],"41":[39,"北九州市八幡東区","祝町"],"42":[39,"北九州市八幡東区","羽衣町"],"43":[39,"北九州市八幡東区","勝山"],"44":[39,"北九州市八幡東区","豊町"],"45":[39,"北九州市八幡東区","河内"],"46":[39,"北九州市八幡東区","田代"],"47":[39,"北九州市八幡東区","景勝町"],"48":[39,"北九州市八幡東区","大蔵"],"49":[39,"北九州市八幡東区","末広町"],"5":[39,"北九州市八幡東区","藤見町"],"50":[39,"北九州市八幡東区","春の町"],"51":[39,"北九州市八幡東区","東丸山町"],"52":[39,"北九州市八幡東区","西丸山町"],"53":[39,"北九州市八幡東区","大谷"],"54":[39,"北九州市八幡東区","天神町"],"55":[39,"北九州市八幡東区","神山町"],"56":[39,"北九州市八幡東区","帆柱"],"57":[39,"北九州市八幡東区","尾倉(大字)"],"58":[39,"北九州市八幡東区","前田(大字)"],"59":[39,"北九州市八幡東区","尾倉(丁目)"],"6":[39,"北九州市八幡東区","諏訪"],"61":[39,"北九州市八幡東区","西本町"],"62":[39,"北九州市八幡東区","平野"],"63":[39,"北九州市八幡東区","東台良町"],"64":[39,"北九州市八幡東区","西台良町"],"65":[39,"北九州市八幡東区","花尾町"],"66":[39,"北九州市八幡東区","祇園原町"],"67":[39,"北九州市八幡東区","祇園"],"68":[39,"北九州市八幡東区","桃園"],"69":[39,"北九州市八幡東区","前田(丁目)"],"7":[39,"北九州市八幡東区","白川町"],"71":[39,"北九州市八幡東区","東田"],"8":[39,"北九州市八幡東区","枝光本町"],"8501":[39,"北九州市八幡東区尾倉","2丁目1-2 吉川工業 株式会社"],"8503":[39,"北九州市八幡東区枝光","2丁目1-15 三島光産 株式会社"],"8505":[39,"北九州市八幡東区平野","2丁目2-1 独立行政法人 国際協力機構 九州国際センター"],"8507":[39,"北九州市八幡東区西本町","3丁目1番1号 株式会社 アステック入江"],"8508":[39,"北九州市八幡東区春の町","1丁目1-1 医療法人社団 新日鐵八幡記念病院"],"8509":[39,"北九州市八幡東区東田","1丁目6-3 ムロオカ商事 株式会社"],"8510":[39,"北九州市八幡東区中央","1丁目1-1 北九州市 八幡東区役所"],"8512":[39,"北九州市八幡東区平野","1丁目6-1 九州国際大学"],"8513":[39,"北九州市八幡東区平野","2丁目5-1 学校法人 九州国際大学"],"8514":[39,"北九州市八幡東区大字枝光","1950-10 株式会社 山本工作所"],"8516":[39,"北九州市八幡東区枝光本町","8番1号 日鉄住金物流八幡 株式会社"],"8518":[39,"北九州市八幡東区山王","1丁目13-15 東亜非破壊検査 株式会社"],"8520":[39,"北九州市八幡東区尾倉","2丁目8-1(八幡郵便局私書箱第7号) 福岡ひびき信用金庫"],"8521":[39,"北九州市八幡東区尾倉","2丁目4-7 月星商事 株式会社"],"8527":[39,"北九州市八幡東区春の町","5丁目9-27 社会福祉法人 恩賜財団済生会支部 福岡県済生会八幡総合病院"],"8528":[39,"北九州市八幡東区平野","2丁目11-1 株式会社 スピナ"],"8530":[39,"北九州市八幡東区川淵町","9-27 太平工業 株式会社 八幡支店"],"8531":[39,"北九州市八幡東区山王","2丁目19-1 株式会社 奥村組 九州支店"],"8533":[39,"北九州市八幡東区山王","1丁目9-10 九築工業 株式会社"],"8534":[39,"北九州市八幡東区尾倉","二丁目6番2号 北九州市立八幡病院"],"8535":[39,"北九州市八幡東区西本町","3丁目2-5 株式会社 菅原"],"8536":[39,"北九州市八幡東区大字前田","企業団地5-1 寒川商事 株式会社"],"8538":[39,"北九州市八幡東区東田","1丁目7番5号 株式会社 有薗製作所"],"8539":[39,"北九州市八幡東区","前田企業団地1-1 株式会社 タカミヤ"],"8555":[39,"北九州市八幡東区大字前田","字大塚1320-4 日鉄住金テックスエンジ 株式会社 北九州事業センター"],"8585":[39,"北九州市八幡東区東田","4丁目1-1 株式会社 スペースワールド"],"8606":[39,"北九州市八幡東区平野","2丁目13-1(八幡郵便局私書箱第2号) 八幡税務署"],"8625":[39,"北九州市八幡東区中央","3丁目1-1(八幡郵便局私書箱第10号) みずほ銀行 北九州支店 八幡出張所"],"9":[39,"北九州市八幡東区","宮田町"]}
