{"0":[39,"福岡市西区"],"1":[39,"福岡市西区","小戸"],"11":[39,"福岡市西区","小呂島"],"1100":[39,"糸島市"],"1101":[39,"糸島市","板持"],"1102":[39,"糸島市","高田"],"1103":[39,"糸島市","池田"],"1104":[39,"糸島市","波多江"],"1105":[39,"糸島市","潤"],"1106":[39,"糸島市","志登"],"1107":[39,"糸島市","波多江駅北"],"1108":[39,"糸島市","波多江駅南"],"1111":[39,"糸島市","泊"],"1112":[39,"糸島市","浦志"],"1113":[39,"糸島市","前原"],"1114":[39,"糸島市","新田"],"1115":[39,"糸島市","油比"],"1116":[39,"糸島市","前原中央"],"1117":[39,"糸島市","前原西"],"1118":[39,"糸島市","前原北"],"1119":[39,"糸島市","前原東"],"1120":[39,"糸島市","神在東"],"1121":[39,"糸島市","荻浦"],"1122":[39,"糸島市","東"],"1123":[39,"糸島市","神在"],"1124":[39,"糸島市","加布里"],"1125":[39,"糸島市","千早新田"],"1126":[39,"糸島市","岩本"],"1127":[39,"糸島市","有田中央"],"1128":[39,"糸島市","篠原東"],"1129":[39,"糸島市","篠原西"],"1130":[39,"糸島市","伊都の杜"],"1131":[39,"糸島市","篠原"],"1132":[39,"糸島市","有田"],"1133":[39,"糸島市","富"],"1134":[39,"糸島市","多久"],"1135":[39,"糸島市","大浦"],"1136":[39,"糸島市","美咲が丘"],"1137":[39,"糸島市","南風台"],"1138":[39,"糸島市","前原駅南"],"1139":[39,"糸島市","前原南"],"1141":[39,"糸島市","蔵持"],"1142":[39,"糸島市","八島"],"1143":[39,"糸島市","高上"],"1144":[39,"糸島市","山北"],"1145":[39,"糸島市","雷山"],"1146":[39,"糸島市","三坂"],"1147":[39,"糸島市","香力"],"1148":[39,"糸島市","神在西"],"1149":[39,"糸島市","千早新田西"],"1151":[39,"糸島市","本"],"1152":[39,"糸島市","飯原"],"1153":[39,"糸島市","長野"],"1154":[39,"糸島市","白糸"],"1155":[39,"糸島市","川付"],"1156":[39,"糸島市","瀬戸"],"1192":[39,"糸島市前原西","1丁目1-1(前原郵便局私書箱第6号) 糸島市役所 本庁舎"],"1193":[39,"糸島市前原東","2丁目7-1(前原郵便局私書箱第3号) 糸島農業協同組合"],"1195":[39,"糸島市波多江","字中川原100 九星飲料工業 株式会社"],"12":[39,"福岡市西区","能古"],"13":[39,"福岡市西区","愛宕浜"],"1301":[39,"糸島市","志摩井田原"],"1302":[39,"糸島市","志摩吉田"],"1303":[39,"糸島市","志摩野北"],"1304":[39,"糸島市","志摩桜井"],"1305":[39,"糸島市","志摩馬場"],"1306":[39,"糸島市","志摩松隈"],"1311":[39,"糸島市","志摩津和崎"],"1312":[39,"糸島市","志摩初"],"1313":[39,"糸島市","志摩稲留"],"1314":[39,"糸島市","志摩師吉"],"1315":[39,"糸島市","志摩稲葉"],"1321":[39,"糸島市","志摩小富士"],"1322":[39,"糸島市","志摩御床"],"1323":[39,"糸島市","志摩小金丸"],"1324":[39,"糸島市","志摩東貝塚"],"1325":[39,"糸島市","志摩西貝塚"],"1331":[39,"糸島市","志摩久家"],"1332":[39,"糸島市","志摩船越"],"1333":[39,"糸島市","志摩新町"],"1334":[39,"糸島市","志摩岐志"],"1335":[39,"糸島市","志摩芥屋"],"1336":[39,"糸島市","志摩姫島"],"1392":[39,"糸島市志摩初","30 糸島市役所 志摩庁舎"],"14":[39,"福岡市西区","豊浜"],"15":[39,"福岡市西区","愛宕"],"1561":[39,"糸島市","曽根"],"1562":[39,"糸島市","井田"],"1563":[39,"糸島市","高来寺"],"1564":[39,"糸島市","大門"],"1571":[39,"糸島市","高祖"],"1572":[39,"糸島市","末永"],"1573":[39,"糸島市","王丸"],"1574":[39,"糸島市","川原"],"1575":[39,"糸島市","西堂"],"1581":[39,"糸島市","瑞梅寺"],"1582":[39,"糸島市","井原"],"1583":[39,"糸島市","三雲"],"1601":[39,"糸島市","二丈深江"],"161":[39,"福岡市西区","今宿東"],"1611":[39,"糸島市","二丈片山"],"1612":[39,"糸島市","二丈松末(下松末)"],"1613":[39,"糸島市","二丈松末(その他)"],"1614":[39,"糸島市","二丈浜窪"],"1615":[39,"糸島市","二丈田中"],"1616":[39,"糸島市","二丈武"],"162":[39,"福岡市西区","今宿青木"],"1621":[39,"糸島市","二丈上深江"],"1622":[39,"糸島市","二丈一貴山"],"1623":[39,"糸島市","二丈石崎"],"1624":[39,"糸島市","二丈満吉"],"1625":[39,"糸島市","二丈長石"],"1626":[39,"糸島市","二丈波呂"],"1627":[39,"糸島市","二丈松国"],"163":[39,"福岡市西区","今宿上ノ原"],"1631":[39,"糸島市","二丈福井"],"164":[39,"福岡市西区","今宿町"],"1641":[39,"糸島市","二丈吉井"],"1642":[39,"糸島市","二丈鹿家"],"165":[39,"福岡市西区","今津"],"166":[39,"福岡市西区","横浜(1～2丁目)"],"167":[39,"福岡市西区","今宿"],"168":[39,"福岡市西区","今宿駅前"],"169":[39,"福岡市西区","今宿西"],"1692":[39,"糸島市二丈深江","1360 糸島市役所 二丈庁舎"],"192":[39,"福岡市西区今宿東","1丁目1-1 三菱電機 株式会社 福岡事業所"],"193":[39,"福岡市西区今宿青木","1042番地1 株式会社 マルタイ"],"2":[39,"福岡市西区","姪の浜"],"201":[39,"福岡市西区","宮浦"],"202":[39,"福岡市西区","西浦"],"203":[39,"福岡市西区","小田"],"204":[39,"福岡市西区","草場"],"205":[39,"福岡市西区","玄界島"],"21":[39,"福岡市西区","大町団地"],"22":[39,"福岡市西区","福重"],"23":[39,"福岡市西区","福重団地"],"24":[39,"福岡市西区","十郎川団地"],"25":[39,"福岡市西区","石丸"],"30":[39,"福岡市西区","室見が丘"],"31":[39,"福岡市西区","橋本(丁目)"],"32":[39,"福岡市西区","戸切"],"33":[39,"福岡市西区","橋本(大字)"],"34":[39,"福岡市西区","田"],"35":[39,"福岡市西区","金武"],"36":[39,"福岡市西区","吉武"],"366":[39,"福岡市西区","横浜(3丁目)"],"367":[39,"福岡市西区","西都"],"37":[39,"福岡市西区","飯盛"],"371":[39,"福岡市西区","飯氏"],"372":[39,"福岡市西区","宇田川原"],"373":[39,"福岡市西区","周船寺"],"374":[39,"福岡市西区","千里"],"375":[39,"福岡市西区","徳永"],"376":[39,"福岡市西区","女原"],"377":[39,"福岡市西区","女原北"],"378":[39,"福岡市西区","徳永北"],"379":[39,"福岡市西区","北原"],"38":[39,"福岡市西区","羽根戸"],"381":[39,"福岡市西区","泉"],"382":[39,"福岡市西区","桑原"],"383":[39,"福岡市西区","田尻"],"384":[39,"福岡市西区","太郎丸"],"385":[39,"福岡市西区","元岡"],"386":[39,"福岡市西区","元浜"],"387":[39,"福岡市西区","富士見"],"388":[39,"福岡市西区","九大新町"],"39":[39,"福岡市西区","西入部"],"395":[39,"福岡市西区大字元岡","744番地 国立大学法人 九州大学"],"41":[39,"福岡市西区","拾六町"],"42":[39,"福岡市西区","壱岐団地"],"43":[39,"福岡市西区","野方"],"44":[39,"福岡市西区","生松台"],"45":[39,"福岡市西区","拾六町団地"],"46":[39,"福岡市西区","西の丘"],"5":[39,"福岡市西区","内浜"],"51":[39,"福岡市西区","下山門団地"],"52":[39,"福岡市西区","下山門"],"53":[39,"福岡市西区","城の原団地"],"54":[39,"福岡市西区","上山門"],"55":[39,"福岡市西区","生の松原"],"6":[39,"福岡市西区","姪浜駅南"],"7":[39,"福岡市西区","愛宕南"],"8501":[39,"福岡市西区内浜","1丁目4-1 福岡市 西区役所"],"8502":[39,"福岡市西区内浜","1丁目3-7 日本年金機構 西福岡年金事務所"],"8504":[39,"福岡市西区姪浜駅南","1丁目9-20 九州電力 株式会社 福岡西営業所"],"8511":[39,"福岡市西区石丸","4-3-1 社会医療法人財団 白十字会 白十字病院"],"8533":[39,"福岡市西区姪の浜","4丁目14-17 医療法人 南川整形外科病院"],"8550":[39,"福岡市西区野方","7丁目780番1 社会福祉法人 博仁会 リハモール福岡"],"8551":[39,"福岡市西区野方","7丁目770 医療法人 博仁会 福岡リハビリテーション病院"],"8552":[39,"福岡市西区姪浜駅南","3丁目8-10 福岡西公共職業安定所"],"8555":[39,"福岡市西区生の松原","3丁目18-8 医療法人 西福岡病院"],"8558":[39,"福岡市西区福重","3丁目1-11 西南自動車工業 株式会社"],"8585":[39,"福岡市西区戸切","2丁目14-45 医療法人財団 華林会 村上華林堂病院"],"8611":[39,"福岡市西区石丸","3-2-1 社会医療法人財団 白十字会 白十字リハビリテーション病院"]}
