{"0":[43,"杵築市"],"1":[43,"杵築市","杵築"],"11":[43,"杵築市","相原"],"12":[43,"杵築市","中"],"13":[43,"杵築市","日野"],"14":[43,"杵築市","本庄"],"15":[43,"杵築市","八坂"],"2":[43,"杵築市","南杵築"],"201":[43,"国東市","安岐町吉松"],"202":[43,"国東市","安岐町瀬戸田"],"203":[43,"国東市","安岐町中園"],"204":[43,"国東市","安岐町成久"],"205":[43,"国東市","安岐町掛樋"],"206":[43,"国東市","安岐町山浦"],"207":[43,"国東市","安岐町油留木"],"21":[43,"杵築市","岩谷"],"211":[43,"国東市","安岐町馬場"],"212":[43,"国東市","安岐町塩屋"],"22":[43,"杵築市","大片平"],"221":[43,"国東市","安岐町西本"],"222":[43,"国東市","安岐町下山口"],"223":[43,"国東市","安岐町大添"],"224":[43,"国東市","安岐町山口"],"23":[43,"杵築市","鴨川"],"231":[43,"国東市","安岐町下原"],"232":[43,"国東市","安岐町向陽台"],"24":[43,"杵築市","船部"],"25":[43,"杵築市","溝井"],"292":[43,"国東市安岐町下原","710 大分キヤノン 株式会社"],"293":[43,"国東市安岐町中園","100 安岐総合支所"],"298":[43,"国東市安岐町下原","1456 国東市民病院"],"3":[43,"杵築市","馬場尾"],"31":[43,"杵築市","狩宿"],"32":[43,"杵築市","奈多"],"33":[43,"杵築市","守江"],"34":[43,"杵築市","横城"],"351":[43,"国東市","安岐町朝来"],"352":[43,"国東市","安岐町明治"],"353":[43,"国東市","安岐町矢川(その他)"],"354":[43,"国東市","安岐町糸永"],"355":[43,"国東市","安岐町富清"],"356":[43,"国東市","安岐町両子"],"4":[43,"杵築市","宮司"],"401":[43,"国東市","武蔵町池ノ内"],"402":[43,"国東市","武蔵町内田"],"404":[43,"国東市","武蔵町成吉"],"405":[43,"国東市","武蔵町麻田"],"406":[43,"国東市","武蔵町丸小野"],"407":[43,"国東市","武蔵町狭間"],"41":[43,"杵築市","大田俣水(天堤)"],"412":[43,"国東市","武蔵町古市"],"414":[43,"国東市","武蔵町手野"],"415":[43,"国東市","武蔵町吉広"],"421":[43,"国東市","武蔵町糸原"],"422":[43,"国東市","武蔵町小城"],"423":[43,"国東市","武蔵町三井寺"],"424":[43,"国東市","武蔵町志和利"],"432":[43,"国東市","武蔵町向陽台"],"498":[43,"国東市武蔵町古市","684 武蔵総合支所"],"5":[43,"杵築市","猪尾"],"500":[43,"国東市"],"501":[43,"国東市","国東町北江"],"502":[43,"国東市","国東町田深"],"503":[43,"国東市","国東町鶴川"],"504":[43,"国東市","国東町安国寺"],"511":[43,"国東市","国東町小原"],"512":[43,"国東市","国東町治郎丸"],"513":[43,"国東市","国東町綱井"],"514":[43,"国東市","国東町重藤"],"521":[43,"国東市","国東町原"],"522":[43,"国東市","国東町岩屋"],"523":[43,"国東市","国東町赤松"],"524":[43,"国東市","国東町横手"],"53":[43,"国東市","安岐町矢川(天堤)"],"531":[43,"国東市","国東町川原"],"532":[43,"国東市","国東町中田"],"533":[43,"国東市","国東町見地"],"534":[43,"国東市","国東町下成仏"],"535":[43,"国東市","国東町成仏"],"6":[43,"杵築市","大内"],"641":[43,"国東市","国東町深江"],"642":[43,"国東市","国東町東堅来"],"643":[43,"国東市","国東町富来浦"],"644":[43,"国東市","国東町浜崎"],"645":[43,"国東市","国東町富来"],"646":[43,"国東市","国東町大恩寺"],"7":[43,"杵築市","片野"],"8":[43,"杵築市","熊野"],"8501":[43,"杵築市大字熊野","1-111 大分キヤノンマテリアル 株式会社"]}
