{"0":[43,"別府市"],"1":[43,"別府市","小坂"],"11":[43,"別府市","内竈"],"12":[43,"別府市","スパランド豊海"],"13":[43,"別府市","古市町"],"14":[43,"別府市","亀川浜田町"],"15":[43,"別府市","国立"],"16":[43,"別府市","野田"],"2":[43,"別府市","関の江新町"],"21":[43,"別府市","亀川中央町"],"22":[43,"別府市","亀川東町"],"23":[43,"別府市","上人ケ浜町"],"24":[43,"別府市","平田町"],"25":[43,"別府市","亀川四の湯町"],"3":[43,"別府市","大所"],"31":[43,"別府市","照波園町"],"32":[43,"別府市","上人本町"],"33":[43,"別府市","上人南"],"34":[43,"別府市","上人仲町"],"35":[43,"別府市","上人西"],"36":[43,"別府市","上平田町"],"37":[43,"別府市","大観山町"],"4":[43,"別府市","湯山"],"41":[43,"別府市","北鉄輪"],"42":[43,"別府市","鉄輪東"],"43":[43,"別府市","井田"],"44":[43,"別府市","風呂本"],"45":[43,"別府市","御幸"],"46":[43,"別府市","鉄輪上"],"5":[43,"別府市","天間"],"801":[43,"別府市","山の口"],"802":[43,"別府市","城島"],"803":[43,"別府市","東山一区"],"804":[43,"別府市","東山二区"],"805":[43,"別府市","枝郷"],"811":[43,"別府市","柳"],"812":[43,"別府市","朝見"],"813":[43,"別府市","両郡橋"],"814":[43,"別府市","浦田"],"815":[43,"別府市","田の口"],"816":[43,"別府市","河内"],"817":[43,"別府市","鳥越"],"818":[43,"別府市","山家"],"819":[43,"別府市","赤松"],"820":[43,"別府市","原町"],"821":[43,"別府市","乙原"],"822":[43,"別府市","観海寺"],"823":[43,"別府市","南立石本町"],"824":[43,"別府市","南立石板地町"],"825":[43,"別府市","南立石八幡町"],"826":[43,"別府市","鶴見園町"],"827":[43,"別府市","南立石二区"],"828":[43,"別府市","山の手町"],"829":[43,"別府市","上原町"],"831":[43,"別府市","堀田"],"832":[43,"別府市","南立石生目町"],"833":[43,"別府市","鶴見(1～18組)"],"834":[43,"別府市","新別府"],"835":[43,"別府市","実相寺"],"836":[43,"別府市","東荘園"],"837":[43,"別府市","荘園北町"],"838":[43,"別府市","荘園"],"839":[43,"別府市","南立石一区"],"840":[43,"別府市","鶴見(大字、番地)"],"841":[43,"別府市","竹の内"],"842":[43,"別府市","小倉"],"843":[43,"別府市","明礬"],"844":[43,"別府市","火売"],"845":[43,"別府市","北中"],"846":[43,"別府市","朝日ケ丘町"],"847":[43,"別府市","馬場"],"848":[43,"別府市","大畑"],"849":[43,"別府市","扇山"],"901":[43,"別府市","中島町"],"902":[43,"別府市","青山町"],"903":[43,"別府市","野口原"],"904":[43,"別府市","南荘園町"],"905":[43,"別府市","上野口町"],"906":[43,"別府市","天満町"],"907":[43,"別府市","幸町"],"908":[43,"別府市","上田の湯町"],"909":[43,"別府市","田の湯町"],"910":[43,"別府市","石垣西"],"911":[43,"別府市","緑丘町"],"912":[43,"別府市","南須賀"],"913":[43,"別府市","春木"],"914":[43,"別府市","中須賀元町"],"915":[43,"別府市","桜ケ丘"],"916":[43,"別府市","中須賀本町"],"917":[43,"別府市","中須賀東町"],"918":[43,"別府市","汐見町"],"919":[43,"別府市","石垣東"],"920":[43,"別府市","北浜"],"921":[43,"別府市","富士見町"],"922":[43,"別府市","船小路町"],"923":[43,"別府市","新港町"],"924":[43,"別府市","餅ケ浜町"],"925":[43,"別府市","若草町"],"926":[43,"別府市","京町"],"927":[43,"別府市","弓ケ浜町"],"928":[43,"別府市","北的ケ浜町"],"929":[43,"別府市","南的ケ浜町"],"930":[43,"別府市","光町"],"931":[43,"別府市","西野口町"],"932":[43,"別府市","野口中町"],"933":[43,"別府市","野口元町"],"934":[43,"別府市","駅前本町"],"935":[43,"別府市","駅前町"],"936":[43,"別府市","中央町"],"937":[43,"別府市","秋葉町"],"938":[43,"別府市","末広町"],"939":[43,"別府市","立田町"],"941":[43,"別府市","南町"],"942":[43,"別府市","千代町"],"943":[43,"別府市","楠町"],"944":[43,"別府市","元町"],"945":[43,"別府市","浜町"],"946":[43,"別府市","松原町"],"947":[43,"別府市","浜脇"]}
